r6api/__init__.py
r6api/auth.py
r6api/default_stats.py
r6api/exceptions.py
r6api/linked_accounts.py
r6api/maps.py
r6api/operators.py
r6api/player.py
r6api/rank_profile.py
r6api/ranks.py
r6api/summaries.py
r6api/trends.py
r6api/url_builder.py
r6api/utils.py
r6api/weapons.py
r6api/constants/__init__.py
r6api/constants/operators.py
r6api/constants/ranks.py
r6api/constants/seasons.py
r6api/constants/weapons.py
r6api-1.0.0.dist-info/LICENSE
r6api-1.0.0.dist-info/METADATA
r6api-1.0.0.dist-info/WHEEL
r6api-1.0.0.dist-info/top_level.txt
r6api-1.0.0.dist-info/RECORD
